finpython/__init__.py
finpython/core.py
finpython/crypto.py
finpython-0.13.dist-info/LICENSE
finpython-0.13.dist-info/METADATA
finpython-0.13.dist-info/WHEEL
finpython-0.13.dist-info/top_level.txt
finpython-0.13.dist-info/RECORD
